pyzapkit/__init__.py
pyzapkit/main.py
pyzapkit-0.1.0.dist-info/METADATA
pyzapkit-0.1.0.dist-info/WHEEL
pyzapkit-0.1.0.dist-info/top_level.txt
pyzapkit-0.1.0.dist-info/RECORD
