Metadata-Version: 2.1
Name: pyzapkit
Version: 0.1.0
Summary: Automatically send Whatsapp messages and files
Home-page: https://github.com/joaosuzuki98/pyzapkit
Author: João Suzuki
License: MIT
Keywords: Automation,Whatsapp
Requires-Dist: PyAutoGUI
Requires-Dist: selenium
